<ch-doc:CriminalHistory xmlns:ch-doc="http://ojbc.org/IEPD/Exchange/CriminalHistory/1.0" xmlns:ansi-nist="http://niem.gov/niem/ansi-nist/2.0" xmlns:ch="http://ojbc.org/IEPD/Extensions/RapSheet/1.0" xmlns:ch-ext="http://ojbc.org/IEPD/Extensions/CriminalHistory/1.0" xmlns:error="http://ojbc.org/IEPD/Extensions/PersonQueryErrorReporting/1.0" xmlns:intel="http://niem.gov/niem/domains/intelligence/2.1" xmlns:jxdm40="http://niem.gov/niem/domains/jxdm/4.0" xmlns:jxdm41="http://niem.gov/niem/domains/jxdm/4.1" xmlns:nc="http://niem.gov/niem/niem-core/2.0" xmlns:pqr="http://ojbc.org/IEPD/Exchange/PersonQueryRequest/1.0" xmlns:psr="http://ojbc.org/IEPD/Extensions/PersonSearchRequest/1.0" xmlns:psr-doc="http://ojbc.org/IEPD/Exchange/PersonSearchRequest/1.0" xmlns:psres="http://ojbc.org/IEPD/Extensions/PersonSearchResults/1.0" xmlns:psres-doc="http://ojbc.org/IEPD/Exchange/PersonSearchResults/1.0" xmlns:s="http://niem.gov/niem/structures/2.0" xmlns:screening="http://niem.gov/niem/domains/screening/2.0" xmlns:usps-states="http://niem.gov/niem/usps_states/2.0" xmlns:warrant="http://ojbc.org/IEPD/Exchange/Warrants/1.0" xmlns:warrant-ext="http://ojbc.org/IEPD/Extensions/Warrants/1.0">
    <ch:RapSheet>
        <ch:Metadata>
            <nc:ReportingOrganizationText>State CHRI</nc:ReportingOrganizationText>
        </ch:Metadata>
        <ch:Introduction>
            <ch:RapSheetRequest>
                <ch:PurposeCode>A</ch:PurposeCode>
                <ch:Attention>**CONFIDENTIAL INFORMATION FOR CRIMINAL JUSTICE AGENCIES ONLY**</ch:Attention>
                <ch:RapSheetPerson>
                    <nc:PersonBirthDate>
                        <nc:Date>1939-04-27</nc:Date>
                    </nc:PersonBirthDate>
                    <nc:PersonName>
                        <nc:PersonGivenName>Marty</nc:PersonGivenName>
                        <nc:PersonMiddleName>M</nc:PersonMiddleName>
                        <nc:PersonSurName>Figueredo</nc:PersonSurName>
                    </nc:PersonName>
                </ch:RapSheetPerson>
            </ch:RapSheetRequest>
        </ch:Introduction>
        <ch:RapSheetPerson s:id="P87">
            <nc:PersonAlternateName>
                <nc:PersonGivenName>Marty K</nc:PersonGivenName>
                <nc:PersonSurName>Figueredo</nc:PersonSurName>
            </nc:PersonAlternateName>
            <nc:PersonBirthDate>
                <nc:Date>1939-04-27</nc:Date>
            </nc:PersonBirthDate>
            <nc:PersonEyeColorText>Black</nc:PersonEyeColorText>
            <nc:PersonHairColorText>Brown</nc:PersonHairColorText>
            <nc:PersonHeightMeasure>
                <nc:MeasurePointValue>66</nc:MeasurePointValue>
                <nc:LengthUnitCode>INH</nc:LengthUnitCode>
            </nc:PersonHeightMeasure>
            <nc:PersonName>
                <nc:PersonGivenName>Marty</nc:PersonGivenName>
                <nc:PersonMiddleName>M</nc:PersonMiddleName>
                <nc:PersonSurName>Figueredo</nc:PersonSurName>
            </nc:PersonName>
            <nc:PersonRaceCode>I</nc:PersonRaceCode>
            <nc:PersonSexCode>M</nc:PersonSexCode>
            <nc:PersonSSNIdentification>
                <nc:IdentificationID>449-22-5601</nc:IdentificationID>
                <nc:IdentificationSourceText>SSA</nc:IdentificationSourceText>
            </nc:PersonSSNIdentification>
            <nc:PersonWeightMeasure>
                <nc:MeasurePointValue>211.4</nc:MeasurePointValue>
                <nc:WeightUnitCode>LBR</nc:WeightUnitCode>
            </nc:PersonWeightMeasure>
            <jxdm40:PersonAugmentation>
                <jxdm40:PersonFBIIdentification>
                    <nc:IdentificationID>698661TN8</nc:IdentificationID>
                    <nc:IdentificationSourceText/>
                </jxdm40:PersonFBIIdentification>
                <jxdm40:PersonStateFingerprintIdentification>
                    <nc:IdentificationID>A9932394</nc:IdentificationID>
                    <nc:IdentificationSourceText/>
                </jxdm40:PersonStateFingerprintIdentification>
            </jxdm40:PersonAugmentation>
        </ch:RapSheetPerson>
        <ch:PersonBiometricsAssociation>
            <nc:PersonReference s:ref="P87"/>
            <nc:Biometric>
                <nc:BiometricValueText>W W \ \ \ ,W A / / /</nc:BiometricValueText>
                <nc:BiometricDescriptionText>Fingerprint Class</nc:BiometricDescriptionText>
            </nc:Biometric>
            <ch:PersonBiometrics/>
        </ch:PersonBiometricsAssociation>
        <nc:Location s:id="L1201491826">
            <nc:LocationAddress>
                <nc:AddressFullText>4282 Baker Avenue Arlington, TX 76010</nc:AddressFullText>
            </nc:LocationAddress>
        </nc:Location>
        <ch:Agency s:id="AGY442213575">
            <nc:OrganizationName>Department of Corrections</nc:OrganizationName>
        </ch:Agency>
        <ch:Agency s:id="AGY692374384">
            <nc:OrganizationName>GEORGETOWN PD</nc:OrganizationName>
        </ch:Agency>
        <nc:ResidenceAssociation>
            <nc:PersonReference s:ref="P87"/>
            <nc:LocationReference s:ref="L1201491826"/>
        </nc:ResidenceAssociation>
        <ch:RapSheetCycle>
            <ch:CycleEarliestDate>
                <nc:Date>2009-08-02</nc:Date>
            </ch:CycleEarliestDate>
            <ch:Supervision s:id="A8806719417SC">
                <nc:ActivityCategoryText>CUSTODY</nc:ActivityCategoryText>
                <nc:ActivityDate>
                    <nc:Date>2009-08-02</nc:Date>
                </nc:ActivityDate>
                <nc:SupervisionCustodyStatus>
                    <nc:StatusDescriptionText>SENT FELON</nc:StatusDescriptionText>
                </nc:SupervisionCustodyStatus>
                <nc:SupervisionRelease>
                    <nc:ActivityDate>
                        <nc:Date>2011-06-10</nc:Date>
                    </nc:ActivityDate>
                </nc:SupervisionRelease>
            </ch:Supervision>
        </ch:RapSheetCycle>
        <ch:RapSheetCycle>
            <ch:CycleEarliestDate>
                <nc:Date>2008-12-27</nc:Date>
            </ch:CycleEarliestDate>
            <ch:Arrest s:id="A8806719417">
                <nc:ActivityDate>
                    <nc:Date>2008-12-27</nc:Date>
                </nc:ActivityDate>
                <jxdm40:ArrestAgencyRecordIdentification>
                    <nc:IdentificationID>505-7968306</nc:IdentificationID>
                </jxdm40:ArrestAgencyRecordIdentification>
                <jxdm40:ArrestCharge>
                    <jxdm40:ChargeDescriptionText/>
                    <jxdm40:ChargeIdentification>
                        <nc:IdentificationID>AC51756213</nc:IdentificationID>
                    </jxdm40:ChargeIdentification>
                    <jxdm40:ChargeSeverityText>FC</jxdm40:ChargeSeverityText>
                    <jxdm40:ChargeTrackingIdentification>
                        <nc:IdentificationID>AC51756213</nc:IdentificationID>
                    </jxdm40:ChargeTrackingIdentification>
                </jxdm40:ArrestCharge>
                <jxdm40:ArrestCharge>
                    <jxdm40:ChargeDescriptionText/>
                    <jxdm40:ChargeDisposition>
                        <nc:DispositionDescriptionText>LACK OF PROS</nc:DispositionDescriptionText>
                    </jxdm40:ChargeDisposition>
                    <jxdm40:ChargeIdentification>
                        <nc:IdentificationID>AC35243255</nc:IdentificationID>
                    </jxdm40:ChargeIdentification>
                    <jxdm40:ChargeSeverityText>MD</jxdm40:ChargeSeverityText>
                    <jxdm40:ChargeTrackingIdentification>
                        <nc:IdentificationID>AC35243255</nc:IdentificationID>
                    </jxdm40:ChargeTrackingIdentification>
                </jxdm40:ArrestCharge>
            </ch:Arrest>
            <ch:CourtAction>
                <jxdm40:CourtCharge>
                    <jxdm40:ChargeDescriptionText/>
                    <jxdm40:ChargeDisposition>
                        <nc:DispositionDate>
                            <nc:Date>2009-08-02</nc:Date>
                        </nc:DispositionDate>
                        <nc:DispositionDescriptionText>GUILTY</nc:DispositionDescriptionText>
                    </jxdm40:ChargeDisposition>
                    <jxdm40:ChargeIdentification>
                        <nc:IdentificationID>AC51756213</nc:IdentificationID>
                    </jxdm40:ChargeIdentification>
                    <jxdm40:ChargeSeverityText>FC</jxdm40:ChargeSeverityText>
                    <jxdm40:ChargeTrackingIdentification>
                        <nc:IdentificationID>AC51756213</nc:IdentificationID>
                    </jxdm40:ChargeTrackingIdentification>
                </jxdm40:CourtCharge>
            </ch:CourtAction>
            <ch:Sentencing>
                <jxdm40:Sentence>
                    <jxdm40:SentenceCharge>
                        <jxdm40:ChargeTrackingIdentification>
                            <nc:IdentificationID>AC51756213</nc:IdentificationID>
                        </jxdm40:ChargeTrackingIdentification>
                    </jxdm40:SentenceCharge>
                    <jxdm40:SentenceDescriptionText>ON 08/02/2009 SUBJECT SENTENCED TO 677 DAYS CONFINEMENT AND A FINE OF $508.15</jxdm40:SentenceDescriptionText>
                </jxdm40:Sentence>
            </ch:Sentencing>
        </ch:RapSheetCycle>
        <ch:ArrestAgencyAssociation>
            <nc:ActivityReference s:ref="A8806719417"/>
            <nc:OrganizationReference s:ref="AGY692374384"/>
        </ch:ArrestAgencyAssociation>
        <ch:SupervisionAgencyAssociation>
            <ch:SupervisionReference s:ref="A8806719417SC"/>
            <nc:OrganizationReference s:ref="AGY442213575"/>
        </ch:SupervisionAgencyAssociation>
    </ch:RapSheet>
</ch-doc:CriminalHistory>
